imagebox/__init__.py
imagebox/config.py
imagebox/handler.py
imagebox/indices.py
imagebox/io.py
imagebox/processor.py
imagebox/utils.py
imagebox-0.0.0.19.dist-info/METADATA
imagebox-0.0.0.19.dist-info/WHEEL
imagebox-0.0.0.19.dist-info/entry_points.txt
imagebox-0.0.0.19.dist-info/top_level.txt
imagebox-0.0.0.19.dist-info/RECORD
